MANIFEST.in
setup.py
app_error_handler/__init__.py
app_error_handler/application_error_handler.py
app_error_handler/exception_handling_service.py
app_error_handler/logging_service.py
app_error_handler/root_exception.py
app_error_handler.egg-info/PKG-INFO
app_error_handler.egg-info/SOURCES.txt
app_error_handler.egg-info/dependency_links.txt
app_error_handler.egg-info/requires.txt
app_error_handler.egg-info/top_level.txt
app_error_handler/interfaces/__init__.py
app_error_handler/interfaces/logging_service_interface.py