Metadata-Version: 1.1
Name: app-error-handler
Version: 1.0.1
Summary: An Alternative to web application error handling
Home-page: https://github.com/raviparekh/webapp-error-handler
Author: Ravi Parekh
Author-email: UNKNOWN
License: MIT
Keywords: error-handling flask-error-handler flask django error handler
Platform: any
Classifier: License :: OSI Approved :: MIT License
Classifier: Programming Language :: Python :: 2.7
Classifier: Programming Language :: Python :: 3.4
Classifier: Intended Audience :: Developers
Classifier: Topic :: Software Development :: Libraries
